README.md
setup.py
fast_api_health_check/__init__.py
fast_api_health_check/health_check.py
fast_api_health_check_louisliu.egg-info/PKG-INFO
fast_api_health_check_louisliu.egg-info/SOURCES.txt
fast_api_health_check_louisliu.egg-info/dependency_links.txt
fast_api_health_check_louisliu.egg-info/requires.txt
fast_api_health_check_louisliu.egg-info/top_level.txt