Metadata-Version: 2.1
Name: fast-api-health-check-louisliu
Version: 0.0.3
Summary: fastapi health check
Home-page: https://github.com/pypa/sampleproject
Author: louisliu
Author-email: liuyx7894@163.com
License: UNKNOWN
Platform: UNKNOWN
Classifier: Programming Language :: Python :: 3
Classifier: License :: OSI Approved :: MIT License
Classifier: Operating System :: OS Independent
Requires-Python: >=3.6
